rubika_lib/Uploader.py
rubika_lib/__init__.py
rubika_lib/_date_time.py
rubika_lib/encryption.py
rubika_lib/lib.py
rubika_lib-1.1.1.dist-info/METADATA
rubika_lib-1.1.1.dist-info/WHEEL
rubika_lib-1.1.1.dist-info/top_level.txt
rubika_lib-1.1.1.dist-info/RECORD
